{
    "id": 25,
    "name": "T-LGL-SURVIVAL-NETWORK-2011",
    "url-publication": "https://doi.org/10.1371/journal.pcbi.1002267",
    "url-model": "https://research.cellcollective.org/?dashboard=true#module/2407:1/tlgl-survival-network-2011/1",
    "keywords": [
        "cell-collective",
        "curated"
    ],
    "variables": 54,
    "inputs": 6,
    "regulations": 195,
    "notes": "### Modifications\n\nThe network is provided without modifications.",
    "bib": "@article{bbm-025,\n  title={Dynamical and structural analysis of a {T} cell survival network identifies novel candidate therapeutic targets for large granular lymphocyte leukemia},\n  author={Saadatpour, Assieh and Wang, Rui-Sheng and Liao, Aijun and Liu, Xin and Loughran, Thomas P and Albert, Istv{\\'a}n and Albert, R{\\'e}ka},\n  journal={PLoS computational biology},\n  volume={7},\n  number={11},\n  pages={e1002267},\n  year={2011},\n  publisher={Public Library of Science San Francisco, USA}\n}"
}