{
    "id": 5,
    "name": "FA-BRCA-PATHWAY",
    "url-publication": "https://doi.org/10.1093/bioinformatics/bts036",
    "url-model": "https://research.cellcollective.org/?dashboard=true#module/1778:1/fa-brca-pathway/1",
    "keywords": [
        "cell-collective",
        "grn-principles",
        "curated",
        "repaired"
    ],
    "variables": 28,
    "inputs": 0,
    "regulations": 123,
    "notes": "### Modifications\n\nThe following changes have been made to make sure the regulatory graph is consistent with the network's update functions:\n\n - Regulation `FAcore (S_17) -> PCNATLS (S_5)` set as non-essential.\n - Regulation `FANCD2I (S_4) -> MRN (S_8)` sign set to `unknown`.\n - Regulation `ATR (S_27) -> NHEJ (S_9)` sign set to `unknown`.\n - Regulation `ssDNARPA (S_16) -> NHEJ (S_9)` sign set to `unknown`.\n - Regulation `FAN1 (S_28) -> XPF (S_20)` sign set to `unknown`.\n - Regulation `FANCD2I (S_4) -> XPF (S_20)` sign set to `unknown`.\n",
    "bib": "@article{bbm-005,\n  title={A Boolean network model of the {FA/BRCA} pathway},\n  author={Rodriguez, Alfredo and Sosa, David and Torres, Leda and Molina, Bertha and Frias, Sara and Mendoza, Luis},\n  journal={Bioinformatics},\n  volume={28},\n  number={6},\n  pages={858--866},\n  year={2012},\n  publisher={Oxford University Press}\n}"
}