{
    "id": 83,
    "name": "SIGNALING-IN-PROSTATE-CANCER",
    "url-publication": "https://doi.org/10.7554/eLife.72626",
    "url-model": "http://ginsim.org/node/252",
    "keywords": [
        "ginsim",
        "curated",
        "repaired"
    ],
    "variables": 122,
    "inputs": 11,
    "regulations": 420,
    "notes": "### Modifications\n\nThe constant update functions of the following variables are erased, since they are effectively inputs: `Acidosis`, `Androgen`, `Carcinogen`, `EGF`, `FGF`, `Hypoxia`, `Nutrients`, `SPOP`, `TGFb`, `TNFalpha`, `fused_event`.\n",
    "bib": "@article{bbm-083,\n  title={Patient-specific Boolean models of signalling networks guide personalised treatments},\n  author={Montagud, Arnau and B{\\'e}al, Jonas and Tobalina, Luis and Traynard, Pauline and Subramanian, Vigneshwari and Szalai, Bence and Alf{\\\"o}ldi, R{\\'o}bert and Pusk{\\'a}s, L{\\'a}szl{\\'o} and Valencia, Alfonso and Barillot, Emmanuel and others},\n  journal={Elife},\n  volume={11},\n  pages={e72626},\n  year={2022},\n  publisher={eLife Sciences Publications Limited}\n}\n"
}